<?xml version="1.0" encoding="utf-8"?>
<!--
    Copyright 2023 ODOOGAP/PROMPTEQUATION LDA
    License LGPL-3.0 or later (http://www.gnu.org/licenses/lgpl).
-->
<odoo>

    <record id="view_website_form" model="ir.ui.view">
        <field name="name">website.form</field>
        <field name="model">website</field>
        <field name="inherit_id" ref="website.view_website_form"/>
        <field name="arch" type="xml">
            <xpath expr="//group[@name='domain']" position="after">
                <group class="mt-5" name="vsf_info">
                    <field name="vsf_mailing_list_id"/>
                    <field name="vsf_payment_success_return_url"/>
                    <field name="vsf_payment_error_return_url"/>
                </group>
            </xpath>
        </field>
    </record>

    <record id="view_website_menu_form" model="ir.ui.view">
        <field name="name">website.menu.form</field>
        <field name="model">website.menu</field>
        <field name="inherit_id" ref="website.website_menus_form_view"/>
        <field name="arch" type="xml">
            <xpath expr="//field[@name='url']" position="after">
                <field name="is_footer"/>
            </xpath>
            <xpath expr="//field[@name='page_id']" position="attributes">
                <attribute name="invisible">1</attribute>
            </xpath>
            <xpath expr="//field[@name='new_window']" position="attributes">
                <attribute name="invisible">1</attribute>
            </xpath>
            <xpath expr="//field[@name='child_id']" position="after">
                <label for="menu_image_ids" string="Images"/>
                <field name="menu_image_ids">
                    <form>
                        <group>
                            <group>
                                <field name="image" widget="image"/>
                                <field name="tag"/>
                                <field name="title"/>
                                <field name="subtitle"/>
                            </group>
                            <group>
                                <field name="sequence"/>
                                <field name="text_color"/>
                                <field name="button_text"/>
                                <field name="button_url"/>
                            </group>
                        </group>
                    </form>
                    <tree>
                        <field name="sequence" widget="handle"/>
                        <field name="image"/>
                        <field name="tag"/>
                        <field name="title"/>
                        <field name="subtitle"/>
                        <field name="text_color"/>
                        <field name="button_text"/>
                        <field name="button_url"/>
                    </tree>
                </field>
            </xpath>
        </field>
    </record>

    <record id="menu_tree" model="ir.ui.view">
        <field name="name">website.menu.tree</field>
        <field name="model">website.menu</field>
        <field name="inherit_id" ref="website.menu_tree"/>
        <field name="arch" type="xml">
            <xpath expr="//field[@name='is_mega_menu']" position="attributes">
                <attribute name="invisible">1</attribute>
            </xpath>
            <xpath expr="//field[@name='new_window']" position="attributes">
                <attribute name="invisible">1</attribute>
            </xpath>
        </field>
    </record>

    <record id="menu_search" model="ir.ui.view">
        <field name="name">website.menu.search</field>
        <field name="model">website.menu</field>
        <field name="inherit_id" ref="website.menu_search"/>
        <field name="arch" type="xml">
            <xpath expr="//field[@name='website_id']" position="after">
                <filter string="Menu" name="is_menu"
                        domain="[('is_footer', '=', False), ('is_mega_menu', '=', False)]"/>
                <filter string="Mega Menu" name="is_mega_menu"
                        domain="[('is_footer', '=', False), ('is_mega_menu', '=', True)]"/>
                <filter string="Footer" name="is_footer"
                        domain="[('is_footer', '=', True), ('is_mega_menu', '=', False)]"/>
            </xpath>
        </field>
    </record>

    <!-- ====== Actions ====================================================
        ==================================================================== -->
    <record id="website.action_website_menu" model="ir.actions.act_window">
        <field name="name">Website Menu</field>
        <field name="res_model">website.menu</field>
        <field name="view_mode">tree,form</field>
        <field name="context">{'search_default_is_menu': 1, 'search_default_group_by_website_id': 1}</field>
        <field name="view_id" ref="website.menu_tree"/>
        <field name="target">current</field>
    </record>

    <record id="action_website_footer" model="ir.actions.act_window">
        <field name="name">Website Footer</field>
        <field name="res_model">website.menu</field>
        <field name="view_mode">tree,form</field>
        <field name="context">{'default_is_footer': True, 'search_default_is_footer': 1, 'search_default_group_by_website_id': 1}</field>
        <field name="view_id" ref="graphql_vuestorefront.menu_tree"/>
        <field name="target">current</field>
    </record>

    <record id="action_website_mega_menu" model="ir.actions.act_window">
        <field name="name">Website Mega Menu</field>
        <field name="res_model">website.menu</field>
        <field name="view_mode">tree,form</field>
        <field name="context">{'default_is_mega_menu': True, 'search_default_is_mega_menu': 1, 'search_default_group_by_website_id': 1}</field>
        <field name="view_id" ref="graphql_vuestorefront.menu_tree"/>
        <field name="target">current</field>
    </record>

</odoo>
